{
  "get": {
    "tags": ["Products"],
    "summary": "List Categories",
    "description": "Get all available product categories.",
    "operationId": "listProductCategories",
    "responses": {
      "200": {
        "description": "List of categories",
        "content": {
          "application/json": {
            "schema": {
              "type": "array",
              "items": {
                "type": "object",
                "properties": {
                  "id": { "type": "string", "format": "uuid" },
                  "name": { "type": "string" },
                  "is_active": { "type": "boolean" }
                }
              }
            }
          }
        }
      }
    }
  },
  "post": {
    "tags": ["Products"],
    "summary": "Create Category",
    "security": [{ "bearerAuth": [] }],
    "requestBody": {
      "content": {
        "application/json": {
          "schema": {
            "type": "object",
            "required": ["name"],
            "properties": {
              "name": { "type": "string", "maxLength": 300 }
            }
          }
        }
      }
    },
    "responses": {
      "201": { "description": "Category created" }
    }
  }
}